CVHSSmoothing/Spline.py
CVHSSmoothing/Spline_PCHIP.py
CVHSSmoothing/Spline_from_Pandas.py
CVHSSmoothing/__init__.py
CVHSSmoothing/dss_util.py
CVHSSmoothing/hydrograph_spline.py
CVHSSmoothing/version.py
CVHSSmoothing-1.1.dist-info/LICENSE
CVHSSmoothing-1.1.dist-info/METADATA
CVHSSmoothing-1.1.dist-info/WHEEL
CVHSSmoothing-1.1.dist-info/top_level.txt
CVHSSmoothing-1.1.dist-info/RECORD
