Metadata-Version: 2.1
Name: CVHSSmoothing
Version: 1.1
Summary: Cubic spline interpolation of hydrographs
Home-page: https://github.com/danhamill/CVHSSmoothing
Download-URL: https://github.com/danhamill/CVHSSmoothing
Author: Daniel Hamill
Author-email: daniel.hamill@hey.com
License: MIT
Classifier: Development Status :: 4 - Beta
Classifier: Intended Audience :: Developers
Classifier: Intended Audience :: Science/Research
Classifier: License :: OSI Approved :: MIT License
Classifier: Operating System :: OS Independent
Classifier: Programming Language :: Python :: 3.9
Classifier: Programming Language :: Python :: 3.10
Classifier: Topic :: Utilities
Classifier: Topic :: Scientific/Engineering :: GIS
License-File: LICENSE
Requires-Dist: numpy
Requires-Dist: pandas
Requires-Dist: scipy
